py_dot/__init__.py
py_dot/core/__init__.py
py_dot/core/dicts.py
py_dot/core/jsons.py
py_dot/core/lists.py
py_dot/core/objects.py
py_dot/core/operator.py
py_dot/core/paths.py
py_dot/core/strings.py
py_dot/core/syntax.py
py_dot/core/timer.py
py_dot/core/date/__init__.py
py_dot/core/date/modify.py
py_dot/core/design/dynamic.py
py_dot/core/design/invokable_value.py
py_dot/core/regex/__init__.py
py_dot/core/route/__init__.py
py_dot/core/route/route.py
py_dot/core/tests/__init__.py
py_dot/core/tests/test_core.py
py_dot/core/tests/test_dicts.py
py_dot/core/tests/test_lists.py
py_dot/core/tests/test_route.py
py_dot/core/tests/test_strings.py
py_dot/core/thread/__init__.py
py_dot/core/thread/thread_safe.py
py_dot/data/__init__.py
py_dot/data/frame.py
py_dot/data/summary_time_unit.py
py_dot/data/tests/__init__.py
py_dot/data/tests/test_data.py
py_dot/data/tests/test_frame.py
py_dot/prompt/__init__.py
py_dot/prompt/tests/prompt_test.py
py_dot/store/__init__.py
py_dot/store/arrange.py
py_dot/store/sqlalchemies/__init__.py
py_dot/store/sqlalchemies/filter_from_query_string.py
py_dot/store/sqlalchemies/filter_from_string.py
py_dot/store/tests/__init__.py
py_dot/store/tests/test_arrange.py
py_dot-0.6.6.dist-info/METADATA
py_dot-0.6.6.dist-info/WHEEL
py_dot-0.6.6.dist-info/RECORD
