Metadata-Version: 2.1
Name: py_dot
Version: 0.6.6
Summary: Python Development Utility Library
Project-URL: Homepage, https://github.com/protyliss/py-dot
Project-URL: Bug Tracker, https://github.com/protyliss/py-dot/issues
Author-email: protyliss <protyliss@gmail.com>
Classifier: Programming Language :: Python :: 3
Classifier: Programming Language :: Python :: 3.11
Requires-Python: >=3.11
